{
  "leads": [
    {
      "id": "1",
      "name": "Rahul Sharma",
      "email": "rahul.sharma@technova.com",
      "source": "Website - Pricing Page",
      "company": "TechNova Solutions",
      "status": "Qualified",
      "aiScore": 95,
      "value": 280000,
      "ownerName": "Priya Mehta",
      "ownerAvatar": "https://images.unsplash.com/photo-1494790108377-be9c29b29330?q=80&w=150",
      "addedOn": "May 20, 10:30 AM",
      "phone": "+91 98765 43210",
      "aiInsights": ["High intent lead", "Visited pricing page 3 times", "Downloaded product brochure", "Interested in Enterprise Plan"]
    },
    {
      "id": "2",
      "name": "Priya Mehta",
      "email": "priya.mehta@acme.com",
      "source": "Facebook - Ad Campaign",
      "company": "Acme Pvt Ltd",
      "status": "Contacted",
      "aiScore": 78,
      "value": 160000,
      "ownerName": "Vikram Patel",
      "ownerAvatar": "https://images.unsplash.com/photo-1507003211169-0a1dd7228f2d?q=80&w=150",
      "addedOn": "May 20, 09:15 AM",
      "phone": "+91 91234 56789",
      "aiInsights": ["Positive response on call", "Interested in CRM modules", "Requests WhatsApp pricing"]
    },
    {
      "id": "3",
      "name": "Amit Verma",
      "email": "amit.verma@innovix.com",
      "source": "LinkedIn - Lead Gen Form",
      "company": "Innovix Tech",
      "status": "New",
      "aiScore": 65,
      "value": 120000,
      "ownerName": "Priya Mehta",
      "ownerAvatar": "https://images.unsplash.com/photo-1494790108377-be9c29b29330?q=80&w=150",
      "addedOn": "May 20, 08:45 AM",
      "phone": "+91 99876 54321",
      "aiInsights": ["Downloaded whitepaper", "Role: Product Manager"]
    },
    {
      "id": "4",
      "name": "Sneha Iyer",
      "email": "sneha.iyer@brightco.com",
      "source": "Instagram - Lead Form",
      "company": "BrightCo",
      "status": "Qualified",
      "aiScore": 88,
      "value": 220000,
      "ownerName": "Anjali Singh",
      "ownerAvatar": "https://images.unsplash.com/photo-1544005313-94ddf0286df2?q=80&w=150",
      "addedOn": "May 19, 07:50 PM",
      "phone": "+91 90012 34567",
      "aiInsights": ["Clicked calendar link", "Interests: Scheduling Automation"]
    },
    {
      "id": "5",
      "name": "Dinesh Kumar",
      "email": "dinesh.kumar@globex.com",
      "source": "Referral - Partner",
      "company": "Globex Corporation",
      "status": "Proposal",
      "aiScore": 70,
      "value": 340000,
      "ownerName": "Rahul Desai",
      "ownerAvatar": "https://images.unsplash.com/photo-1500648767791-00dcc994a43e?q=80&w=150",
      "addedOn": "May 19, 06:20 PM",
      "phone": "+91 87654 32109",
      "aiInsights": ["Under legal contract review", "Requested custom SLA terms"]
    },
    {
      "id": "6",
      "name": "Neha Patel",
      "email": "neha.patel@futurex.com",
      "source": "Website - Contact Us",
      "company": "FutureX Solutions",
      "status": "New",
      "aiScore": 52,
      "value": 90000,
      "ownerName": "Priya Mehta",
      "ownerAvatar": "https://images.unsplash.com/photo-1494790108377-be9c29b29330?q=80&w=150",
      "addedOn": "May 19, 05:10 PM",
      "phone": "+91 78901 23456",
      "aiInsights": ["Inquired about pricing tiers", "Startup profile"]
    },
    {
      "id": "7",
      "name": "Vikram Singh",
      "email": "vikram.singh@infini.com",
      "source": "YouTube - Ad Campaign",
      "company": "Infini Systems",
      "status": "Unqualified",
      "aiScore": 30,
      "value": 0,
      "ownerName": "Vikram Patel",
      "ownerAvatar": "https://images.unsplash.com/photo-1507003211169-0a1dd7228f2d?q=80&w=150",
      "addedOn": "May 19, 04:30 PM",
      "phone": "+91 96432 10987",
      "aiInsights": ["Wrong contact number", "Competitor research pattern"]
    }
  ],
  "leadsSourceData": [
    { "name": "Website", "value": 987, "color": "#4f46e5" },
    { "name": "Facebook", "value": 517, "color": "#3b82f6" },
    { "name": "Instagram", "value": 353, "color": "#ec4899" },
    { "name": "LinkedIn", "value": 235, "color": "#06b6d4" },
    { "name": "Referral", "value": 141, "color": "#f59e0b" },
    { "name": "Others", "value": 117, "color": "#64748b" }
  ]
}
